Metadata-Version: 2.1
Name: py3exiv2
Version: 0.12.0
Summary: A Python3 binding to the library exiv2
Home-page: https://launchpad.net/py3exiv2
Author: Vincent Vande Vyvre
Author-email: vincent.vandevyvre@oqapy.eu
License: GPL-3
Keywords: exiv2 pyexiv2 EXIF IPTC XMP image metadata
Platform: UNKNOWN
Classifier: Development Status :: 5 - Production/Stable
Classifier: Intended Audience :: Developers
Classifier: Topic :: Software Development
Classifier: License :: OSI Approved :: GNU General Public License v3 (GPLv3)
Classifier: Programming Language :: C++
Classifier: Programming Language :: Python :: 3.3
Classifier: Programming Language :: Python :: 3.4
Classifier: Programming Language :: Python :: 3.5
Classifier: Programming Language :: Python :: 3.6
Classifier: Programming Language :: Python :: 3.7
Classifier: Programming Language :: Python :: 3.8
Classifier: Programming Language :: Python :: 3.9
Classifier: Programming Language :: Python :: 3.10
Classifier: Programming Language :: Python :: 3.11
License-File: COPYING
